ast_visitors/__init__.py
ast_visitors/param_visitor.py
ast_visitors/port_visitor.py
ast_visitors/submodule_inst_visitor.py
core/__init__.py
core/module.py
tables/__init__.py
tables/param.py
tables/port.py
utils/__init__.py
utils/attr_utils.py
utils/string_utils.py
svql_minimal-0.1.0.dist-info/LICENSE
svql_minimal-0.1.0.dist-info/METADATA
svql_minimal-0.1.0.dist-info/WHEEL
svql_minimal-0.1.0.dist-info/top_level.txt
svql_minimal-0.1.0.dist-info/RECORD
