Metadata-Version: 2.2
Name: svql-minimal
Version: 0.1.0
Summary: Test package
Home-page: https://github.com/etched-ai/svql
Author: sathvik
Author-email: sathvik <sathvik@etched.com>
License: MIT
Classifier: Programming Language :: Python :: 3
Requires-Python: >=3.6
License-File: LICENSE
Dynamic: author
Dynamic: home-page
Dynamic: requires-python
